abst/__init__.py
abst/__version__.py
abst/cfg_func.py
abst/config.py
abst/dialogs.py
abst/main.py
abst/tools.py
abst/wrappers.py
abst/bastion_support/__init__.py
abst/bastion_support/bastion_scheduler.py
abst/bastion_support/oci_bastion.py
abst/cli_commands/__init__.py
abst/cli_commands/context/__init__.py
abst/cli_commands/context/commands.py
abst/cli_commands/cp_cli/__init__.py
abst/cli_commands/cp_cli/commands.py
abst/cli_commands/create_cli/__init__.py
abst/cli_commands/create_cli/commands.py
abst/cli_commands/helm_cli/__init__.py
abst/cli_commands/helm_cli/commands.py
abst/cli_commands/kubectl_cli/__init__.py
abst/cli_commands/kubectl_cli/commands.py
abst/cli_commands/parallel/__init__.py
abst/cli_commands/parallel/commands.py
abst/cli_commands/ssh_cli/__init__.py
abst/cli_commands/ssh_cli/commands.py
abst/cli_commands/ssh_cli/utils.py
abst/notifier/__init__.py
abst/notifier/version_notifier.py
abst/sharing/__init__.py
abst/sharing/local_broadcast.py
abst/sharing/tests/__init__.py
abst/sharing/tests/test_functionality.py
abst/utils/__init__.py
abst/utils/misc_funcs.py
abst-2.3.59.dist-info/licenses/LICENSE.md
abst-2.3.59.dist-info/METADATA
abst-2.3.59.dist-info/WHEEL
abst-2.3.59.dist-info/entry_points.txt
abst-2.3.59.dist-info/top_level.txt
abst-2.3.59.dist-info/zip-safe
abst-2.3.59.dist-info/RECORD
