Metadata-Version: 2.4
Name: abst
Version: 2.3.59
Summary: CLI Command making OCI Bastion and kubernetes usage simple and fast
Home-page: https://github.com/jiri-otoupal/abst
Author: Jiri Otoupal
Author-email: jiri-otoupal@ips-database.eu
License: MIT
Keywords: Auto OCI Bastion
Classifier: Development Status :: 4 - Beta
Classifier: Intended Audience :: Developers
Classifier: Programming Language :: Python :: 3.7
Classifier: Programming Language :: Python :: 3.8
Classifier: Programming Language :: Python :: 3.9
Classifier: Programming Language :: Python :: 3.10
Classifier: Programming Language :: Python :: 3.11
Classifier: Programming Language :: Python :: 3.12
Requires-Python: >=3.7,<4
License-File: LICENSE.md
Requires-Dist: click
Requires-Dist: rich
Requires-Dist: inquirerpy
Requires-Dist: oci==2.150.0
Requires-Dist: lastversion
Requires-Dist: semantic_version
Requires-Dist: pyperclip
Requires-Dist: bext
Requires-Dist: deepmerge~=2.0
Provides-Extra: dev
Requires-Dist: black==22.*; extra == "dev"
Dynamic: author
Dynamic: author-email
Dynamic: classifier
Dynamic: description
Dynamic: description-content-type
Dynamic: home-page
Dynamic: keywords
Dynamic: license
Dynamic: license-file
Dynamic: provides-extra
Dynamic: requires-dist
Dynamic: requires-python
Dynamic: summary
